pipModuleTest/__init__.py
pipModuleTest/add.py
pipModuleTest/subtract.py
pipModuleTest-0.0.1.dist-info/METADATA
pipModuleTest-0.0.1.dist-info/WHEEL
pipModuleTest-0.0.1.dist-info/top_level.txt
pipModuleTest-0.0.1.dist-info/RECORD
